graphprint/__init__.py
graphprint-0.1.0.dist-info/LICENSE
graphprint-0.1.0.dist-info/METADATA
graphprint-0.1.0.dist-info/WHEEL
graphprint-0.1.0.dist-info/top_level.txt
graphprint-0.1.0.dist-info/RECORD
